[{"items":[{"id":"m2","name":"Margherita Pizza","price":"12.99","description":"A classic pizza with fresh mozzarella, tomatoes, and basil on a thin and crispy crust.","image":"images/margherita-pizza.jpg","quantity":2},{"id":"m1","name":"Mac & Cheese","price":"8.99","description":"Creamy cheddar cheese mixed with perfectly cooked macaroni, topped with crispy breadcrumbs. A classic comfort food.","image":"images/mac-and-cheese.jpg","quantity":1}],"customer":{"name":"Bobi","email":"bob@test.com","street":"Rr. Komuna Parisit","postal-code":"1500","city":"Tirane"},"id":"632.8090086734992"},{"items":[{"id":"m8","name":"Sushi Roll Platter","price":"15.99","description":"An assortment of fresh sushi rolls including California, Spicy Tuna, and Eel Avocado.","image":"images/sushi-roll-platter.jpg","quantity":1}],"customer":{"name":"Nishi","email":"nishi@test.com","street":"nishist","postal-code":"12345","city":"nishic"},"id":"874.7877444092816"},{"items":[{"id":"m2","name":"Margherita Pizza","price":"12.99","description":"A classic pizza with fresh mozzarella, tomatoes, and basil on a thin and crispy crust.","image":"images/margherita-pizza.jpg","quantity":1}],"customer":{"name":"Endri Elbasani","email":"email@test.com","street":"kruje","postal-code":"1501","city":"kruje"},"id":"621.3693259836252"},{"items":[{"id":"m2","name":"Margherita Pizza","price":"12.99","description":"A classic pizza with fresh mozzarella, tomatoes, and basil on a thin and crispy crust.","image":"images/margherita-pizza.jpg","quantity":1}],"customer":{"name":"Endri Elbasani","email":"email@test.com","street":"kruje","postal-code":"1501","city":"kruje"},"id":"480.9562330353514"},{"items":[{"id":"m2","name":"Margherita Pizza","price":"12.99","description":"A classic pizza with fresh mozzarella, tomatoes, and basil on a thin and crispy crust.","image":"images/margherita-pizza.jpg","quantity":1}],"customer":{"name":"Endri Elbasani","email":"email@test.com","street":"kruje","postal-code":"1501","city":"kruje"},"id":"330.30279749657507"},{"items":[{"id":"m2","name":"Margherita Pizza","price":"12.99","description":"A classic pizza with fresh mozzarella, tomatoes, and basil on a thin and crispy crust.","image":"images/margherita-pizza.jpg","quantity":1}],"customer":{"name":"Endri Elbasani","email":"email@test.com","street":"kruje","postal-code":"1501","city":"kruje"},"id":"586.169210085155"},{"items":[{"id":"m2","name":"Margherita Pizza","price":"12.99","description":"A classic pizza with fresh mozzarella, tomatoes, and basil on a thin and crispy crust.","image":"images/margherita-pizza.jpg","quantity":1}],"customer":{"name":"Endri Elbasani","email":"email@test.com","street":"kruje","postal-code":"1501","city":"kruje"},"id":"562.4930027379229"},{"items":[{"id":"m2","name":"Margherita Pizza","price":"12.99","description":"A classic pizza with fresh mozzarella, tomatoes, and basil on a thin and crispy crust.","image":"images/margherita-pizza.jpg","quantity":1}],"customer":{"name":"Endri Elbasani","email":"email@test.com","street":"kruje","postal-code":"1501","city":"kruje"},"id":"222.08179587860454"},{"items":[{"id":"m2","name":"Margherita Pizza","price":"12.99","description":"A classic pizza with fresh mozzarella, tomatoes, and basil on a thin and crispy crust.","image":"images/margherita-pizza.jpg","quantity":1}],"customer":{"name":"Endri Elbasani","email":"email@test.com","street":"kruje","postal-code":"1501","city":"kruje"},"id":"455.6979851569505"},{"items":[{"id":"m2","name":"Margherita Pizza","price":"12.99","description":"A classic pizza with fresh mozzarella, tomatoes, and basil on a thin and crispy crust.","image":"images/margherita-pizza.jpg","quantity":1}],"customer":{"name":"Endri Elbasani","email":"email@test.com","street":"kruje","postal-code":"1501","city":"kruje"},"id":"748.8584461530934"},{"items":[{"id":"m2","name":"Margherita Pizza","price":"12.99","description":"A classic pizza with fresh mozzarella, tomatoes, and basil on a thin and crispy crust.","image":"images/margherita-pizza.jpg","quantity":1}],"customer":{"name":"Endri Elbasani","email":"email@test.com","street":"kruje","postal-code":"1501","city":"kruje"},"id":"519.5708638626495"},{"items":[{"id":"m2","name":"Margherita Pizza","price":"12.99","description":"A classic pizza with fresh mozzarella, tomatoes, and basil on a thin and crispy crust.","image":"images/margherita-pizza.jpg","quantity":1}],"customer":{"name":"Endri Elbasani","email":"email@test.com","street":"kruje","postal-code":"1501","city":"kruje"},"id":"230.12113588369232"},{"items":[{"id":"m2","name":"Margherita Pizza","price":"12.99","description":"A classic pizza with fresh mozzarella, tomatoes, and basil on a thin and crispy crust.","image":"images/margherita-pizza.jpg","quantity":1}],"customer":{"name":"Endri Elbasani","email":"email@test.com","street":"kruje","postal-code":"1501","city":"kruje"},"id":"854.7648662827332"},{"items":[{"id":"m2","name":"Margherita Pizza","price":"12.99","description":"A classic pizza with fresh mozzarella, tomatoes, and basil on a thin and crispy crust.","image":"images/margherita-pizza.jpg","quantity":1}],"customer":{"name":"Endri Elbasani","email":"email@test.com","street":"kruje","postal-code":"1501","city":"kruje"},"id":"673.2963679345436"},{"items":[{"id":"m2","name":"Margherita Pizza","price":"12.99","description":"A classic pizza with fresh mozzarella, tomatoes, and basil on a thin and crispy crust.","image":"images/margherita-pizza.jpg","quantity":1}],"customer":{"name":"Endri Elbasani","email":"email@test.com","street":"kruje","postal-code":"1501","city":"kruje"},"id":"576.137172963136"},{"items":[{"id":"m2","name":"Margherita Pizza","price":"12.99","description":"A classic pizza with fresh mozzarella, tomatoes, and basil on a thin and crispy crust.","image":"images/margherita-pizza.jpg","quantity":1}],"customer":{"name":"Endri Elbasani","email":"email@test.com","street":"kruje","postal-code":"1501","city":"kruje"},"id":"378.902718365256"},{"items":[{"id":"m2","name":"Margherita Pizza","price":"12.99","description":"A classic pizza with fresh mozzarella, tomatoes, and basil on a thin and crispy crust.","image":"images/margherita-pizza.jpg","quantity":1}],"customer":{"name":"Endri Elbasani","email":"email@test.com","street":"kruje","postal-code":"1501","city":"kruje"},"id":"81.60268114066139"},{"items":[{"id":"m2","name":"Margherita Pizza","price":"12.99","description":"A classic pizza with fresh mozzarella, tomatoes, and basil on a thin and crispy crust.","image":"images/margherita-pizza.jpg","quantity":1}],"customer":{"name":"Endri Elbasani","email":"email@test.com","street":"kruje","postal-code":"1501","city":"kruje"},"id":"506.84535031276255"},{"items":[{"id":"m2","name":"Margherita Pizza","price":"12.99","description":"A classic pizza with fresh mozzarella, tomatoes, and basil on a thin and crispy crust.","image":"images/margherita-pizza.jpg","quantity":1}],"customer":{"name":"Endri Elbasani","email":"email@test.com","street":"kruje","postal-code":"1501","city":"kruje"},"id":"415.2326581235102"},{"items":[{"id":"m2","name":"Margherita Pizza","price":"12.99","description":"A classic pizza with fresh mozzarella, tomatoes, and basil on a thin and crispy crust.","image":"images/margherita-pizza.jpg","quantity":1}],"customer":{"name":"Endri Elbasani","email":"email@test.com","street":"kruje","postal-code":"1501","city":"kruje"},"id":"216.96828120818478"},{"items":[{"id":"m2","name":"Margherita Pizza","price":"12.99","description":"A classic pizza with fresh mozzarella, tomatoes, and basil on a thin and crispy crust.","image":"images/margherita-pizza.jpg","quantity":1}],"customer":{"name":"Endri Elbasani","email":"email@test.com","street":"kruje","postal-code":"1501","city":"kruje"},"id":"133.56178997242063"},{"items":[{"id":"m2","name":"Margherita Pizza","price":"12.99","description":"A classic pizza with fresh mozzarella, tomatoes, and basil on a thin and crispy crust.","image":"images/margherita-pizza.jpg","quantity":1}],"customer":{"name":"Endri Elbasani","email":"email@test.com","street":"kruje","postal-code":"1501","city":"kruje"},"id":"184.85548855207324"},{"items":[{"id":"m2","name":"Margherita Pizza","price":"12.99","description":"A classic pizza with fresh mozzarella, tomatoes, and basil on a thin and crispy crust.","image":"images/margherita-pizza.jpg","quantity":1}],"customer":{"name":"Endri Elbasani","email":"email@test.com","street":"kruje","postal-code":"1501","city":"kruje"},"id":"803.4294549399993"},{"items":[{"id":"m2","name":"Margherita Pizza","price":"12.99","description":"A classic pizza with fresh mozzarella, tomatoes, and basil on a thin and crispy crust.","image":"images/margherita-pizza.jpg","quantity":1}],"customer":{"name":"Endri Elbasani","email":"email@test.com","street":"kruje","postal-code":"1501","city":"kruje"},"id":"365.8929762103025"},{"items":[{"id":"m2","name":"Margherita Pizza","price":"12.99","description":"A classic pizza with fresh mozzarella, tomatoes, and basil on a thin and crispy crust.","image":"images/margherita-pizza.jpg","quantity":1}],"customer":{"name":"Endri Elbasani","email":"email@test.com","street":"kruje","postal-code":"1501","city":"kruje"},"id":"174.73932948879823"},{"items":[{"id":"m2","name":"Margherita Pizza","price":"12.99","description":"A classic pizza with fresh mozzarella, tomatoes, and basil on a thin and crispy crust.","image":"images/margherita-pizza.jpg","quantity":1}],"customer":{"name":"Endri Elbasani","email":"email@test.com","street":"kruje","postal-code":"1501","city":"kruje"},"id":"980.8282302822815"},{"items":[{"id":"m2","name":"Margherita Pizza","price":"12.99","description":"A classic pizza with fresh mozzarella, tomatoes, and basil on a thin and crispy crust.","image":"images/margherita-pizza.jpg","quantity":1}],"customer":{"name":"Endri Elbasani","email":"email@test.com","street":"kruje","postal-code":"1501","city":"kruje"},"id":"336.94368690636975"},{"items":[{"id":"m2","name":"Margherita Pizza","price":"12.99","description":"A classic pizza with fresh mozzarella, tomatoes, and basil on a thin and crispy crust.","image":"images/margherita-pizza.jpg","quantity":1}],"customer":{"name":"Endri Elbasani","email":"email@test.com","street":"kruje","postal-code":"1501","city":"kruje"},"id":"283.53832930565216"},{"items":[{"id":"m2","name":"Margherita Pizza","price":"12.99","description":"A classic pizza with fresh mozzarella, tomatoes, and basil on a thin and crispy crust.","image":"images/margherita-pizza.jpg","quantity":1}],"customer":{"name":"Endri Elbasani","email":"email@test.com","street":"kruje","postal-code":"1501","city":"kruje"},"id":"280.08500924567414"},{"items":[{"id":"m2","name":"Margherita Pizza","price":"12.99","description":"A classic pizza with fresh mozzarella, tomatoes, and basil on a thin and crispy crust.","image":"images/margherita-pizza.jpg","quantity":1}],"customer":{"name":"Endri Elbasani","email":"email@test.com","street":"kruje","postal-code":"1501","city":"kruje"},"id":"344.02350672412973"},{"items":[{"id":"m2","name":"Margherita Pizza","price":"12.99","description":"A classic pizza with fresh mozzarella, tomatoes, and basil on a thin and crispy crust.","image":"images/margherita-pizza.jpg","quantity":1}],"customer":{"name":"Endri Elbasani","email":"email@test.com","street":"kruje","postal-code":"1501","city":"kruje"},"id":"890.5236704069788"},{"items":[{"id":"m2","name":"Margherita Pizza","price":"12.99","description":"A classic pizza with fresh mozzarella, tomatoes, and basil on a thin and crispy crust.","image":"images/margherita-pizza.jpg","quantity":1}],"customer":{"name":"Endri Elbasani","email":"email@test.com","street":"kruje","postal-code":"1501","city":"kruje"},"id":"220.34472390153036"}]